README.rst
setup.py
weather_yahoo/__init__.py
weather_yahoo/__main__.py
weather_yahoo/main.py
weather_yahoo/unit.py
weather_yahoo/weather_yahoo.py
weather_yahoo/helpers/__init__.py
weather_yahoo/helpers/add_leading_zero.py
weather_yahoo/objects/__init__.py
weather_yahoo/objects/astronomy_obj.py
weather_yahoo/objects/atmosphere_obj.py
weather_yahoo/objects/condition_obj.py
weather_yahoo/objects/forecast_obj.py
weather_yahoo/objects/item_obj.py
weather_yahoo/objects/location_obj.py
weather_yahoo/objects/unit_obj.py
weather_yahoo/objects/weather_obj.py
weather_yahoo/objects/wind_obj.py
yahoo_api.egg-info/PKG-INFO
yahoo_api.egg-info/SOURCES.txt
yahoo_api.egg-info/dependency_links.txt
yahoo_api.egg-info/entry_points.txt
yahoo_api.egg-info/not-zip-safe
yahoo_api.egg-info/requires.txt
yahoo_api.egg-info/top_level.txt