Metadata-Version: 1.1
Name: yahoo-api
Version: 1.0.1
Summary: A Python Wrapper for the Yahoo Weather API.
Home-page: https://github.com/hanshof/yahoo_weather_api
Author: Hans Hofstaetter
Author-email: hanshof@mailbox.org
License: MIT
Keywords: weather,api,yahoo
Platform: UNKNOWN
Classifier: Intended Audience :: Developers
Classifier: License :: OSI Approved :: MIT License
Classifier: Topic :: Software Development :: Libraries
Classifier: Programming Language :: Python
Classifier: Programming Language :: Python :: 2.7
Classifier: Programming Language :: Python :: 3
Classifier: Programming Language :: Python :: 3.3
Classifier: Programming Language :: Python :: 3.4
Classifier: Programming Language :: Python :: 3.5
Classifier: Programming Language :: Python :: 3.6
